xjy_rsa_util/__init__.py
xjy_rsa_util/xjy_rsa_util.py
xjy_util-0.1.4.dist-info/licenses/LICENSE
xjy_util-0.1.4.dist-info/METADATA
xjy_util-0.1.4.dist-info/WHEEL
xjy_util-0.1.4.dist-info/top_level.txt
xjy_util-0.1.4.dist-info/RECORD
